odoo/addons/base_transaction_id/README.rst
odoo/addons/base_transaction_id/__init__.py
odoo/addons/base_transaction_id/__manifest__.py
odoo/addons/base_transaction_id/i18n/ar.po
odoo/addons/base_transaction_id/i18n/base_transaction_id.pot
odoo/addons/base_transaction_id/i18n/bg.po
odoo/addons/base_transaction_id/i18n/bs.po
odoo/addons/base_transaction_id/i18n/ca.po
odoo/addons/base_transaction_id/i18n/cs.po
odoo/addons/base_transaction_id/i18n/de.po
odoo/addons/base_transaction_id/i18n/el_GR.po
odoo/addons/base_transaction_id/i18n/en_GB.po
odoo/addons/base_transaction_id/i18n/es.po
odoo/addons/base_transaction_id/i18n/es_CR.po
odoo/addons/base_transaction_id/i18n/es_EC.po
odoo/addons/base_transaction_id/i18n/es_ES.po
odoo/addons/base_transaction_id/i18n/es_MX.po
odoo/addons/base_transaction_id/i18n/et.po
odoo/addons/base_transaction_id/i18n/fi.po
odoo/addons/base_transaction_id/i18n/fr.po
odoo/addons/base_transaction_id/i18n/fr_CH.po
odoo/addons/base_transaction_id/i18n/gl.po
odoo/addons/base_transaction_id/i18n/hr.po
odoo/addons/base_transaction_id/i18n/hr_HR.po
odoo/addons/base_transaction_id/i18n/hu.po
odoo/addons/base_transaction_id/i18n/id.po
odoo/addons/base_transaction_id/i18n/it.po
odoo/addons/base_transaction_id/i18n/ja.po
odoo/addons/base_transaction_id/i18n/lt.po
odoo/addons/base_transaction_id/i18n/lv.po
odoo/addons/base_transaction_id/i18n/mk.po
odoo/addons/base_transaction_id/i18n/mn.po
odoo/addons/base_transaction_id/i18n/nb_NO.po
odoo/addons/base_transaction_id/i18n/nl.po
odoo/addons/base_transaction_id/i18n/nl_BE.po
odoo/addons/base_transaction_id/i18n/pl.po
odoo/addons/base_transaction_id/i18n/pt.po
odoo/addons/base_transaction_id/i18n/pt_BR.po
odoo/addons/base_transaction_id/i18n/pt_PT.po
odoo/addons/base_transaction_id/i18n/ro.po
odoo/addons/base_transaction_id/i18n/ru.po
odoo/addons/base_transaction_id/i18n/sk_SK.po
odoo/addons/base_transaction_id/i18n/sl.po
odoo/addons/base_transaction_id/i18n/sv.po
odoo/addons/base_transaction_id/i18n/th.po
odoo_addon_base_transaction_id-18.0.1.0.0.5.dist-info/METADATA
odoo_addon_base_transaction_id-18.0.1.0.0.5.dist-info/WHEEL
odoo_addon_base_transaction_id-18.0.1.0.0.5.dist-info/top_level.txt
odoo_addon_base_transaction_id-18.0.1.0.0.5.dist-info/RECORD
